mrgenerator/__init__.py
mrgenerator/generator.py
mrgenerator/infos.py
mrgenerator/readme.py
mrgenerator/run.py
mrgenerator/utils.py
mrgenerator/model/__init__.py
mrgenerator/model/readme.py
mrgenerator/templates/__init__.py
mrgenerator/templates/default.pmd
markdown_readme_generator-0.1.4.dist-info/LICENSE
markdown_readme_generator-0.1.4.dist-info/METADATA
markdown_readme_generator-0.1.4.dist-info/WHEEL
markdown_readme_generator-0.1.4.dist-info/entry_points.txt
markdown_readme_generator-0.1.4.dist-info/top_level.txt
markdown_readme_generator-0.1.4.dist-info/RECORD
