Metadata-Version: 2.1
Name: markdown-readme-generator
Version: 0.1.4
Summary: readme generator
Home-page: https://github.com/pedroermarinho/markdown-readme-generator
Author: Pedro Marinho
Author-email: pedro.marinho238@gmail.com
License: MIT
Project-URL: Documentation, https://github.com/pedroermarinho/markdown-readme-generator
Project-URL: Say Thanks!, https://github.com/pedroermarinho/markdown-readme-generator
Project-URL: Source, https://github.com/pedroermarinho/markdown-readme-generator
Project-URL: Tracker, https://github.com/pedroermarinho/markdown-readme-generator/issues
Keywords: markdown readme mrgenerator generator
Platform: UNKNOWN
Classifier: Programming Language :: Python :: 3
Classifier: License :: OSI Approved :: MIT License
Classifier: Operating System :: OS Independent
Requires-Python: ~=3.6
